{
    "AC": "Air Condition",
    "AI": "Architect / Interior",
    "BHE": "Boiling House Equipment",
    "BRB": "Bridge Bearing",
    "BRC": "Bridge Construction",
    "BCO": "Bridge Consultancy",
    "CW": "Civil work",
    "CON": "Consultancy",
    "DRO": "Drone",
    "FF": "Fire Fighting",
    "FRI": "Fire resistant items",
    "GDT": "Garden Tools",
    "GIS": "GIS Survey",
    "HW": "Horticulture Work",
    "HKS": "Housekeeping Services",
    "LI": "Laboratory Items",
    "LEE": "Lift / Elevator / Escalator",
    "MPS": "Manpower Supply",
    "ME": "Medical Equipments",
    "MRW": "Meter Reading Work",
    "MIS": "Misc.",
    "PST": "Pre school kit / TLM",
    "SEQ": "Security Equipments",
    "SEC": "Security Services",
    "SW": "Software",
    "SP": "Solar Products",
    "TD": "Tubewell Drilling"
  }
  